titanicazertyui/__init__.py
titanicazertyui/get_data.py
titanicazertyui/model.py
titanicazertyui/pipeline.py
titanicazertyui/preprocessing.py
titanicazertyui/response_json.py
titanicazertyui-0.0.1.dist-info/LICENSE
titanicazertyui-0.0.1.dist-info/METADATA
titanicazertyui-0.0.1.dist-info/WHEEL
titanicazertyui-0.0.1.dist-info/top_level.txt
titanicazertyui-0.0.1.dist-info/RECORD
